{
  "description": "✂  Tools & Supplies I Recommend: https://goo.gl/Y7KKhY\n$  Support Black Magic Craft on Patreon: https://goo.gl/ZZ4vBf\n\n➳  http://www.blackmagiccraft.ca\n➳  Facebook: https://goo.gl/hvNgQL\n\n(As an Amazon Associate I earn from qualifying purchases)\n\nWoodland Scenics Trees: \n(3\"-5\" Deciduous Set) http://amzn.to/2vpoF8f\n(8\" Premium Trees) http://amzn.to/2vLTvIW\n\nRhode SmartLav Microphone: \n(USA) http://amzn.to/2uvOzZb (Canada) http://amzn.to/2hRrFpd\n\nZoom H1: \n(USA) http://amzn.to/2fxTbHt (Canada)http://amzn.to/2vtz550\n\nBlue Yeti Microphone: \n(USA) http://amzn.to/2vpFjVj (Canada) http://amzn.to/2hQUx0w\n\nCuticle Scissors: http://amzn.to/2hRPOf0\n\n3M Respirator: http://amzn.to/2vpJErl\n\nMy music projects\n\nDistorted Memory: https://distortedmemory.bandcamp.com/\n\nCakebuilder: https://cakebuilder.bandcamp.com/\n\nWatch The Magus (Soundtrack composed by me): \nhttps://vimeo.com/18862721\n\n\nBlack Magic Craft special Q&A episode. 30 viewer questions answered.\n\n\n\n\n\n\n\n\n\n\n\n\n\n\n\n\nBlack Magic Craft intro music by Black Magic Craft\n\nBackground music:\nKevin MacLeod (incompetech.com)\nhttp://creativecommons.org/licenses/by/3.0/",
  "id": "gnNe3AivTQI",
  "position": 48,
  "publishedAt": 1502243042,
  "thumbnails": {
    "default": "https://i.ytimg.com/vi/gnNe3AivTQI/sddefault.jpg",
    "large": "https://i.ytimg.com/vi/gnNe3AivTQI/maxresdefault.jpg",
    "small": "https://i.ytimg.com/vi/gnNe3AivTQI/mqdefault.jpg"
  },
  "title": "Special Episode: Your Questions Answered! (Black Magic Craft Episode 049)"
}
