[
  {
    "content": "Oh hey guys Adam Scottie here welcome to",
    "start": 6
  },
  {
    "content": "the craft today's project I wanted to show you this door that I made I made it",
    "start": 15
  },
  {
    "content": "for my death perch tower and you can see it in the play videos it's a it's kind",
    "start": 20
  },
  {
    "content": "of on the shadow side so it's not easy to see so you'll get to see a nice",
    "start": 25
  },
  {
    "content": "close-up here in this video but I want to talk about it because I use two",
    "start": 28
  },
  {
    "content": "different techniques to create the door I wanted to have kind of like an",
    "start": 32
  },
  {
    "content": "amorphous surface like it's shifting and moving so I thought that'd be kind of",
    "start": 39
  },
  {
    "content": "neat to do with sculpey clay and then I bent the the outer part with the",
    "start": 43
  },
  {
    "content": "standard door technique so let's go the table I'll show you the door and show",
    "start": 47
  },
  {
    "content": "you what I'm talking about so here's the neat door I made for my a tower at the",
    "start": 51
  },
  {
    "content": "death perch peak the players are investigating these giants this ancient",
    "start": 60
  },
  {
    "content": "rates race of extinct Giants that would dabble in what the guy called eldritch",
    "start": 66
  },
  {
    "content": "magic and it was just kind of chaos magic in and modern magic users don't",
    "start": 71
  },
  {
    "content": "use it because it's so dangerous but so a lot of the stuff that other stuff is",
    "start": 76
  },
  {
    "content": "infused with this magic it can be unpredictable now this door could cause",
    "start": 79
  },
  {
    "content": "madness if the players didn't correctly get through but they did so that wasn't",
    "start": 84
  },
  {
    "content": "a problem but let me give you a little closer look at the door here you can see",
    "start": 89
  },
  {
    "content": "the swirling that I did on the door and I did both sides as I came out really",
    "start": 93
  },
  {
    "content": "neat and then I just did this was a skull plate and then I just did a",
    "start": 99
  },
  {
    "content": "cardboard frame and slid that over in so I made the door first then measured the",
    "start": 103
  },
  {
    "content": "frame and slid it in and then I used a little bead to give it some decoration",
    "start": 108
  },
  {
    "content": "so I think that came out really nice and really was a great accent to the tower",
    "start": 112
  },
  {
    "content": "so I'm gonna do this a little differently this time I'm showing you",
    "start": 118
  },
  {
    "content": "the door first and then I'm gonna talk about actually how I made the door as",
    "start": 122
  },
  {
    "content": "opposed to reverse because I thought it would help to see the door to see to",
    "start": 127
  },
  {
    "content": "talk for me to talk about the techniques that I used with it so now I'm going to",
    "start": 132
  },
  {
    "content": "go back to the table and show you some show you the techniques and some",
    "start": 136
  },
  {
    "content": "different ways that you can do too the store now bidding is the door here",
    "start": 139
  },
  {
    "content": "for reference so I'll have it closed by him I need to talk about anything so the",
    "start": 145
  },
  {
    "content": "first order by business was to make the swirly part of the door and I decided I",
    "start": 150
  },
  {
    "content": "would go with super skully and I've shown you that before and that's this",
    "start": 156
  },
  {
    "content": "stuff and it works great you just sculpt it out it has unlimited working time you",
    "start": 159
  },
  {
    "content": "sculpt it out and then you bake it to 75 in your oven then you're done now the",
    "start": 165
  },
  {
    "content": "trick is to get you know it's square like this and flat enough that it will",
    "start": 171
  },
  {
    "content": "fit in this type of thing so what I do is I have got a pasta maker okay I just",
    "start": 176
  },
  {
    "content": "bought this as a craft store I wasn't super expensive and you can make",
    "start": 184
  },
  {
    "content": "different sizes by turning this knob so I'll just put the clay in crank it and",
    "start": 188
  },
  {
    "content": "make a sheet okay so that's how I was able to get the thin",
    "start": 194
  },
  {
    "content": "part for the door but what I did was I wanted up on both sides so I made two",
    "start": 197
  },
  {
    "content": "thin sheets of scully and then carved the detail into the door itself now what",
    "start": 203
  },
  {
    "content": "I use for the detail and the door was I use these crochet needles okay a little",
    "start": 212
  },
  {
    "content": "better look at those all right you can get these at any big box store or craft",
    "start": 218
  },
  {
    "content": "store I like them because they have a curved tip and when you can drag it",
    "start": 224
  },
  {
    "content": "through the material and make the detail you can also kind of I use it to kind of",
    "start": 230
  },
  {
    "content": "squish it in and make the holes in the in the front where it was kind of sink",
    "start": 237
  },
  {
    "content": "holes and then use the smaller one to do kind of drag it through and make the",
    "start": 242
  },
  {
    "content": "details so that came out really nice but the trip to getting the door the correct",
    "start": 245
  },
  {
    "content": "size for both sides was I made a I made a cardboard template it was the size of",
    "start": 254
  },
  {
    "content": "this I rolled it out at my pasta machine so it was all equal width and then I put",
    "start": 258
  },
  {
    "content": "it down and then cut out the two square or the two rectangle parts",
    "start": 264
  },
  {
    "content": "and did the detail out so what I do is when I'm doing something like this and",
    "start": 271
  },
  {
    "content": "eat a really easy way to have it put it on a surface so you don't have to you",
    "start": 275
  },
  {
    "content": "can sculpt on the surface and then put it directly in the oven is to just use",
    "start": 282
  },
  {
    "content": "aluminum foil okay so what I did is I squeezed it out of the pasta machine put",
    "start": 285
  },
  {
    "content": "the piece on the lumina Moyle then I use my template and put it on",
    "start": 296
  },
  {
    "content": "made two different copies of the door with just a cardboard template and then",
    "start": 301
  },
  {
    "content": "I cut around it with this blade tool so I just put the black clay on this on",
    "start": 305
  },
  {
    "content": "this aluminum foil put the template on it cut around it then move the template",
    "start": 311
  },
  {
    "content": "here and cut around the next part and then just took all the excess off so I",
    "start": 317
  },
  {
    "content": "basically was left with two rectangle pieces that were the same size that I",
    "start": 320
  },
  {
    "content": "was going to used for the door then I just used my crochet needles and",
    "start": 325
  },
  {
    "content": "sculpted the swirls into the door and then then just bake it and then what I",
    "start": 329
  },
  {
    "content": "did was I took the took the two pieces the two small pieces and glued them back",
    "start": 336
  },
  {
    "content": "to back together so it made each side of the door and then I used my template and",
    "start": 342
  },
  {
    "content": "I was able to do the frame of the door out just this is just out of cardboard",
    "start": 348
  },
  {
    "content": "the frame and the base of this card stock and cardboard and then I just used",
    "start": 351
  },
  {
    "content": "covered up the edge with our standard door technique so that's really all",
    "start": 355
  },
  {
    "content": "there is to it the the sculpting can be really versatile as far as making stuff",
    "start": 360
  },
  {
    "content": "like this also the scope ly like I said the skull B is nice because it doesn't",
    "start": 369
  },
  {
    "content": "dry you're not living it to a certain amount of time so if you start working",
    "start": 373
  },
  {
    "content": "on it you can't finish it or you know whatever you can let it sit and come",
    "start": 378
  },
  {
    "content": "back to it so you know that's great and and wooden foil is the perfect thing to",
    "start": 383
  },
  {
    "content": "use because you can set your work on it especially something flat like this you",
    "start": 390
  },
  {
    "content": "can set your work on it without having to try to peel it up and then put it on",
    "start": 394
  },
  {
    "content": "something so you just put the aluminum foil",
    "start": 398
  },
  {
    "content": "directly in the oven and you're good to go",
    "start": 400
  },
  {
    "content": "so that's it that's that's really how you can make cool stuff like this and",
    "start": 402
  },
  {
    "content": "with with some skully detail and I'll see you next time on the craft hey you",
    "start": 407
  },
  {
    "content": "yeah you back here huh I know we're short but would they expect you're the",
    "start": 417
  },
  {
    "content": "short tip watch longer episodes if you want Jesus quit bugging me",
    "start": 421
  },
  {
    "content": "hey and make sure you join the forum too much for that oh yeah and have a magical",
    "start": 425
  },
  {
    "content": "craft a sick day",
    "start": 430
  }
]
