[
  {
    "content": "why lock here welcome back today let's",
    "start": 10
  },
  {
    "content": "kick it old school won't add to our collection of clip-on features for our",
    "start": 15
  },
  {
    "content": "dungeon tiles so real quick let's brush up on how we make these clip foundations",
    "start": 18
  },
  {
    "content": "remember that our walls are 1/4 inch thick so we start with double corrugated",
    "start": 27
  },
  {
    "content": "cardboard because it's a quarter inch thick and cut the center of the sandwich",
    "start": 31
  },
  {
    "content": "but a half inch less the height so if you want your final clip to be 2 inches",
    "start": 36
  },
  {
    "content": "wide and one-and-a-half inches tall you would cut this 2 inches wide and 1 inch",
    "start": 40
  },
  {
    "content": "tall then with chipboard or cereal box cut to pieces to the desired size so",
    "start": 45
  },
  {
    "content": "this one here I'm doing is 2 inches by one and a half inches of course you",
    "start": 52
  },
  {
    "content": "shouldn't go any wider than 2 inches if you adhere to that rule then you know",
    "start": 57
  },
  {
    "content": "it'll always fit all of your tiles including the worst case scenario which",
    "start": 61
  },
  {
    "content": "is the dead end geometry and then some thin cardstock or even just paper rip a",
    "start": 65
  },
  {
    "content": "strip and hot glue it to cover the corrugation notice we have a 1/2 inch",
    "start": 72
  },
  {
    "content": "tall gap underneath and that's what's going to grip the wall paint it to match",
    "start": 80
  },
  {
    "content": "your dungeon I keep it simple black bomb kitchen sponge to dab on some dark grey",
    "start": 85
  },
  {
    "content": "and then dab on some light gray so to make the map I'm going to go to",
    "start": 104
  },
  {
    "content": "Google search for a fantasy map and we'll limit this to images and just sort",
    "start": 115
  },
  {
    "content": "of scroll look for one that we like and I'm thinking this one here looks pretty",
    "start": 121
  },
  {
    "content": "good so let's check that one out and we'll click View image to make it to go",
    "start": 128
  },
  {
    "content": "and look at the actual source right click and copy image I don't go to",
    "start": 132
  },
  {
    "content": "Microsoft Word and we'll do a paste good there it is",
    "start": 138
  },
  {
    "content": "and if we go to format we can change the width I'm going to make it a little less",
    "start": 146
  },
  {
    "content": "than 2 inches actually so that it's well within the clip on foundation so 1.9",
    "start": 150
  },
  {
    "content": "inches should be good yeah that's a little tall I'm just gonna make it quite",
    "start": 155
  },
  {
    "content": "some tall good that's fine alright so that easy and this is ready for printing",
    "start": 160
  },
  {
    "content": "just for sake of robustness I'm going to glue stick this and double it over to",
    "start": 172
  },
  {
    "content": "make it double thick paper and then just cut it out with scissors",
    "start": 177
  },
  {
    "content": "then hot glue it onto the foundation use toothpicks or matchsticks to add a frame",
    "start": 189
  },
  {
    "content": "if you want to I like it as is how about some creeping vines so prior to painting",
    "start": 194
  },
  {
    "content": "add lines using your hot glue gun thin beads go slowly after painting up the",
    "start": 206
  },
  {
    "content": "dungeon scheme paint the vines green then optionally take your homemade",
    "start": 216
  },
  {
    "content": "sawdust flocking paint on some white PVA glue and flock in hindsight I should",
    "start": 225
  },
  {
    "content": "have only applied glue about half the vines and also used a darker color flock",
    "start": 237
  },
  {
    "content": "so live and learn now you won't make that mistake you can always do real",
    "start": 241
  },
  {
    "content": "simple magic trick kits here's a bead and a clear green marble as hot glue",
    "start": 247
  },
  {
    "content": "them together and then hot glue them to the foundation",
    "start": 251
  },
  {
    "content": "and lastly let's do a waterspout hot glue on a bead and then unfold a",
    "start": 268
  },
  {
    "content": "paperclip and form it into an arc inject some hot glue into that bead and insert",
    "start": 274
  },
  {
    "content": "paperclip and chop it to length so that it's flush with the bottom of the clip",
    "start": 279
  },
  {
    "content": "on on a scrap of card stock hot glue the other end of the paper clip and then",
    "start": 289
  },
  {
    "content": "tease glue outward from there to make it look like splashing then coat the entire",
    "start": 295
  },
  {
    "content": "paperclip with hot glue and sort of tease it paint up the water with blues",
    "start": 302
  },
  {
    "content": "of your choice and before we go to the table I'd like to take a moment to thank",
    "start": 307
  },
  {
    "content": "all wcv sponsors this week I draw your attention to Hiro's horde which is an",
    "start": 317
  },
  {
    "content": "excellent resource for 3d printed scenery including but not limited to",
    "start": 323
  },
  {
    "content": "Altru tiles products so if you're into 3d printing even if it's just to",
    "start": 327
  },
  {
    "content": "supplement your conventional crafting it is worth a click to check it out and see",
    "start": 331
  },
  {
    "content": "what's what alright let's throw down some tiles and",
    "start": 335
  },
  {
    "content": "see what we can do if you're new to the channel you can check out episodes one",
    "start": 339
  },
  {
    "content": "through four or my first live stream for how to make these dungeon tiles so we'll",
    "start": 343
  },
  {
    "content": "go ahead here and we'll clip on the water spout and the magic orb thing the",
    "start": 349
  },
  {
    "content": "map we'll put that at the dead end and the creeping vines we'll use that as a",
    "start": 356
  },
  {
    "content": "clip to hold two tiles together throw a couple other decor on here",
    "start": 360
  },
  {
    "content": "and a couple of miniatures cardstock miniatures alright let's check this out",
    "start": 367
  },
  {
    "content": "episode 21 has those scrolls and books in case you're interested in those you",
    "start": 374
  },
  {
    "content": "can see the map on the table that's done exactly as we did in this episode it's",
    "start": 379
  },
  {
    "content": "just glued on to a table and I I folded it so that it hung over the edge like",
    "start": 383
  },
  {
    "content": "that so that's pretty cool you could see how you might I don't know use the map",
    "start": 388
  },
  {
    "content": "feature as part of the players layer or something like that",
    "start": 392
  },
  {
    "content": "potions episode 7 cardstock miniatures episode 9 of course you could paint up",
    "start": 395
  },
  {
    "content": "the water is acid or poison or whatever you like for a trap so I am why lock",
    "start": 402
  },
  {
    "content": "thank you for joining me and I'll see you next time",
    "start": 407
  },
  {
    "content": "",
    "start": 410
  }
]
