[
  {
    "content": "in the beloved Star Trek episode the trouble with tribbles we're introduced",
    "start": 4
  },
  {
    "content": "to the new TV and slime devil when they Klingon corax compares a Kirk to the",
    "start": 9
  },
  {
    "content": "devil and an insult that Pavel check off is not too happy to hear but that was",
    "start": 13
  },
  {
    "content": "interesting I mean Tsar Trekkies had no idea what it looked like but it just",
    "start": 19
  },
  {
    "content": "kind of stuck with me I think at that point on Deep Space nine Keiko O'Brien",
    "start": 23
  },
  {
    "content": "has a schoolroom that has a panel with a comparative xenobiology and you can see",
    "start": 27
  },
  {
    "content": "the very right-hand corner there is a picture of the denebians slime devil and",
    "start": 32
  },
  {
    "content": "this has taken all this artwork here on this panel is taken from the Starfleet",
    "start": 37
  },
  {
    "content": "medical reference manual published in 1977 and this is what I based my denie",
    "start": 40
  },
  {
    "content": "bein slime devil on hey guys here's my interpretation of the slime devil you",
    "start": 45
  },
  {
    "content": "can see I have a back sloping head with tubes coming up the giant I imagine it",
    "start": 50
  },
  {
    "content": "could breathe underwater or mud and I got this kind idea from the picture from",
    "start": 55
  },
  {
    "content": "the medical manual some vicious teeth there and I was really going for a frog",
    "start": 58
  },
  {
    "content": "like appearance which it seems to have like in the pictures from the medical",
    "start": 62
  },
  {
    "content": "manual I made it slimy I give it some red color to denote the devil status",
    "start": 66
  },
  {
    "content": "very powerful back legs that it could leap up in a surprise or pounce on prey",
    "start": 71
  },
  {
    "content": "and there we go there's my interpretation of the denebians slime",
    "start": 76
  },
  {
    "content": "devil",
    "start": 81
  }
]
