[
  {
    "content": "hey crafters damn Scottie here welcome to the dams gravity today we're going to",
    "start": 19
  },
  {
    "content": "do a special door and this door was built using the same techniques from my",
    "start": 24
  },
  {
    "content": "door video it's just out of cardboard I take it like a cathedral door but I had",
    "start": 31
  },
  {
    "content": "a really cool design to the front of the door so it was super easy and cheap so",
    "start": 35
  },
  {
    "content": "let's go to the table I'll show you how I did that",
    "start": 40
  },
  {
    "content": "so to start I want to show you these these little stall rings I got I got",
    "start": 52
  },
  {
    "content": "these last Halloween at the dollar store and also you know sit you can save",
    "start": 57
  },
  {
    "content": "containers that you're going to throw away that you had food in just wash them",
    "start": 61
  },
  {
    "content": "out these containers make great storage for anything yeah you know that you were",
    "start": 64
  },
  {
    "content": "going to store for your crafts this kind of stuff this was just a little cheese",
    "start": 69
  },
  {
    "content": "container that I had made and I glass and so I use it to store these rings but",
    "start": 74
  },
  {
    "content": "anyways I got a couple packs of these rings at the dollar store the Staller",
    "start": 78
  },
  {
    "content": "store is a great place to go on Halloween go and just buy a bunch of",
    "start": 81
  },
  {
    "content": "stuff and they're so cheap it's all just a dollar each so collect I just collect",
    "start": 86
  },
  {
    "content": "this stuff for the time when I'll need it so basically these are skull rings",
    "start": 90
  },
  {
    "content": "and I'm going to use these for our part of our door project so unfortunately",
    "start": 94
  },
  {
    "content": "they have this little thing on the back so just take care of that pretty easily",
    "start": 100
  },
  {
    "content": "let's grab pair of scissors and then just snip those off and if",
    "start": 104
  },
  {
    "content": "there's any excess you can snip it off dear parts content",
    "start": 112
  },
  {
    "content": "alright so now I end up with a little skull which is nice and I'm gonna use",
    "start": 120
  },
  {
    "content": "that to apply that to our door so now we'll uh we'll bring the doors out and",
    "start": 127
  },
  {
    "content": "go ahead and do that here are my stone doors I made so these are from AJ's",
    "start": 133
  },
  {
    "content": "crypt and these will be to the final room so I did them the same way I did",
    "start": 150
  },
  {
    "content": "the dungeon I used the black spray texture and I did a little bit of gray",
    "start": 155
  },
  {
    "content": "around the edge to give it some in definition so you can see those stone",
    "start": 158
  },
  {
    "content": "doors there now I want to add the skulls to the front so I've taken the skull and",
    "start": 162
  },
  {
    "content": "I've painted it base black with flat blade flat black spray paint so now I",
    "start": 168
  },
  {
    "content": "will just grab my glue gun my handy glue gun and I'll put some glue on the back",
    "start": 174
  },
  {
    "content": "of that generous um house all right so now we're going to do the",
    "start": 179
  },
  {
    "content": "same with the second door and then we're going to come back for some details so",
    "start": 196
  },
  {
    "content": "those are looking good but I really want to get give them kind of an eldritch",
    "start": 200
  },
  {
    "content": "look so I'm going to do is I'm going to take my glue gun and add some wisps",
    "start": 203
  },
  {
    "content": "coming off the skulls and it's hard to see in the camera because this is clear",
    "start": 208
  },
  {
    "content": "but I'm going to paint these so they'll really pop out",
    "start": 220
  },
  {
    "content": "so you might be will see that a little bit",
    "start": 235
  },
  {
    "content": "okay now I'll do the same to the other one and we'll come back for some",
    "start": 240
  },
  {
    "content": "painting okay now remember what you're working with this kind of detail you",
    "start": 243
  },
  {
    "content": "won't get a little bit of they're hard to see but you'll get a little bit of",
    "start": 249
  },
  {
    "content": "wisps on your work sometimes so just wipe those are pretty easy to wipe off",
    "start": 251
  },
  {
    "content": "or just rub off if you can't get them off you can only use it you can always",
    "start": 258
  },
  {
    "content": "use tweezers to do that too so just a little tip a little side tip about",
    "start": 262
  },
  {
    "content": "getting wisps on your projects and this happens with just about anything use",
    "start": 266
  },
  {
    "content": "glue gun glue gun with so just keep that in mind for all you new people doing",
    "start": 270
  },
  {
    "content": "this kind of stuff all right I've got us in here for a pretty close look now and",
    "start": 276
  },
  {
    "content": "what I'm going to do is I'm going to paint this that same kind of green that",
    "start": 280
  },
  {
    "content": "I used when I did the runes on AJ's Creek so what I use is this it's",
    "start": 284
  },
  {
    "content": "actually a lime sorbet acrylic craft paint and so I've got a fairly thin",
    "start": 290
  },
  {
    "content": "brush and then what I'm going to do is I'm going to paint those tendrils that",
    "start": 296
  },
  {
    "content": "are kind of coming off the skull there you know just take your time with this",
    "start": 299
  },
  {
    "content": "so give some dimensionality to that design also we'll paint the skull the",
    "start": 316
  },
  {
    "content": "same way so you know start painting the skull so what I'll do is I'll finish",
    "start": 325
  },
  {
    "content": "this up and come back and give you a look at it",
    "start": 337
  },
  {
    "content": "so here we go look at that that actually just went from a pretty cool stone door",
    "start": 341
  },
  {
    "content": "to just like a super kick-ass looking door so what I'm gonna do is I'm gonna",
    "start": 345
  },
  {
    "content": "hit this with a little bit of spray gloss on the green and then I'm going to",
    "start": 353
  },
  {
    "content": "which I won't show I'll just do that and then what I'm going to do is I'm going",
    "start": 360
  },
  {
    "content": "to put the card stock on the bottom like I do for all my doors and I'll show it",
    "start": 365
  },
  {
    "content": "on the tile you can see what it looks like I am actually gonna do a little bit",
    "start": 369
  },
  {
    "content": "more with this I'm going to add a little bit of shading I'm going to use a a",
    "start": 373
  },
  {
    "content": "metallic sequin black so I have on my palettes just acrylic craft paint and",
    "start": 378
  },
  {
    "content": "I'm gonna paint the eye sockets with it in the news socket",
    "start": 385
  },
  {
    "content": "let's gonna do a little bit of shade so I'm going to wet down the black I kind",
    "start": 410
  },
  {
    "content": "of do follow that line of the mold there",
    "start": 416
  },
  {
    "content": "easier now I'm going to do a little bit of the",
    "start": 427
  },
  {
    "content": "teeth about the dividers between the teeth",
    "start": 437
  },
  {
    "content": "all right so I like it so now it is ready and I will put that I'll just",
    "start": 457
  },
  {
    "content": "spray some gloss on it a little bit of gloss with a spray can and then we'll",
    "start": 463
  },
  {
    "content": "come back and when I show you like I said so here are double doors and I've",
    "start": 468
  },
  {
    "content": "got the base on there just a three-quarter inch piece of cardstock",
    "start": 473
  },
  {
    "content": "and put it on the bottom now you can see that a little bit of gloss on there I",
    "start": 477
  },
  {
    "content": "just sprayed it a touch and just easier than putting I didn't really want to",
    "start": 481
  },
  {
    "content": "thick of a gloss on there so I use the spray now you can use any spray I just",
    "start": 486
  },
  {
    "content": "use a Kryolan satin clear spray just a touch and you can use that for other",
    "start": 490
  },
  {
    "content": "objects but it's good for like just giving a slight gloss to something if",
    "start": 496
  },
  {
    "content": "you if you really want to have the gloss I would do that I would do the water",
    "start": 501
  },
  {
    "content": "base if you really want to be wet looking but I just kind of wanted that",
    "start": 504
  },
  {
    "content": "touch and some protection for the the tendrils and everything on the door so",
    "start": 507
  },
  {
    "content": "now I'm going to go to the tile and show you what it looks like",
    "start": 512
  },
  {
    "content": "so here are the doors on our tile and they really fit in I think look great",
    "start": 525
  },
  {
    "content": "with the rest of the the style of the tile so there we go and when the players",
    "start": 530
  },
  {
    "content": "enter the room they can open the doors so that players get the doors open they",
    "start": 537
  },
  {
    "content": "can swing them this way and you can see that the the bases",
    "start": 542
  },
  {
    "content": "really match into the tile itself so you really can't see the bases very well",
    "start": 545
  },
  {
    "content": "they they blend pretty well into that so and the players can enter the last",
    "start": 549
  },
  {
    "content": "chamber so looking good and we'll have some more crafts with this for the crypt",
    "start": 554
  },
  {
    "content": "in further episodes hey crafters I hope you've enjoyed this",
    "start": 560
  },
  {
    "content": "episode of the dance craft make sure to subscribe and I have tons of other",
    "start": 565
  },
  {
    "content": "videos as you can see I am the originator of the 2.5 D method of",
    "start": 570
  },
  {
    "content": "crafting tiles I also do dirt cheap terrain for the table if all this",
    "start": 574
  },
  {
    "content": "intrigues you make sure you check out all the videos below also join my forum",
    "start": 578
  },
  {
    "content": "we have lots of great crafters on there who give advice I have a link above and",
    "start": 583
  },
  {
    "content": "below and last but not least remember go forth and craft",
    "start": 587
  },
  {
    "content": "you",
    "start": 602
  }
]
