[
  {
    "content": "hello everyone why lock here Happy New",
    "start": 8
  },
  {
    "content": "Year the holidays have come and gone my favorite time of year really special",
    "start": 14
  },
  {
    "content": "time for me it's all about being with the ones that",
    "start": 18
  },
  {
    "content": "you love packaging oh yes the best time of the year cornucopia influx of",
    "start": 21
  },
  {
    "content": "cardboard and all kinds of good stuff look at this Cuisinart Oven thing I",
    "start": 26
  },
  {
    "content": "don't even know what it is but look what it came with yea these packing inserts",
    "start": 31
  },
  {
    "content": "are like I thought perfect for some sort of alien structure and now I'm not the",
    "start": 35
  },
  {
    "content": "first person to use them for this purpose but nonetheless I thought I",
    "start": 39
  },
  {
    "content": "would show you how I used them to make my necron tomb world right so packing",
    "start": 42
  },
  {
    "content": "inserts these are often included in electronics and stuff like that I'm just",
    "start": 50
  },
  {
    "content": "gonna take it and cut away some of the lip give it a nice clean edge then I'm",
    "start": 53
  },
  {
    "content": "gonna base it on foam board so put the container on there and just trace around",
    "start": 57
  },
  {
    "content": "it with I don't know three-quarter inch of margin cut that out and then if",
    "start": 61
  },
  {
    "content": "you're able peel the paper off one side ready board from the Dollar Tree is",
    "start": 65
  },
  {
    "content": "really good for this but it isn't totally necessary it just makes the next",
    "start": 69
  },
  {
    "content": "step a little easier which is to take a fresh blade pretty far extended and",
    "start": 72
  },
  {
    "content": "taper the edge like this knife blade in an extreme angle and draw it back and",
    "start": 77
  },
  {
    "content": "forth as opposed to pushing that'll give you a nice clean cuts now line the edge",
    "start": 82
  },
  {
    "content": "of the container with hot glue and stick it on then for good measure another bead",
    "start": 87
  },
  {
    "content": "of hot glue at the scene give it about 20 seconds to start cooling and then you",
    "start": 92
  },
  {
    "content": "can splay it out with a brisk swipe from your finger hot glue cools quicker than",
    "start": 96
  },
  {
    "content": "you might realize I have a knack for this after four years of working with",
    "start": 100
  },
  {
    "content": "hot glue for like everyday but if in doubt just use the nozzle to spread it",
    "start": 103
  },
  {
    "content": "out then a base coat in black I like to brush on black acrylic because it's much",
    "start": 107
  },
  {
    "content": "darker true or black then you get from typical spray cans place the cheap ones",
    "start": 112
  },
  {
    "content": "takes a lot longer but is worth it oh and I forgot something got a flock the",
    "start": 116
  },
  {
    "content": "base white PVA glue such as Elmer's glue all nice solid coat on the perimeter",
    "start": 121
  },
  {
    "content": "spread it out nice and even with a brush and then dumps and I use quikrete",
    "start": 125
  },
  {
    "content": "construction sand from the home improvement store good because of its",
    "start": 130
  },
  {
    "content": "varying sized aggregate few hours and that's all dry time to get",
    "start": 133
  },
  {
    "content": "some black on that as well having a nice watery brush will help the paint to flow",
    "start": 139
  },
  {
    "content": "better into the sand via capillary action without being too diluted that",
    "start": 143
  },
  {
    "content": "you need a second coat another hour and that's dry take a gray of your choice",
    "start": 147
  },
  {
    "content": "and dry brush if you're new to this stuff that just means load the bristles",
    "start": 153
  },
  {
    "content": "with paint but then immediately work it back off onto the pallet so there's only",
    "start": 157
  },
  {
    "content": "a little bit left on the bristles and it's basically dry then lightly swipe at",
    "start": 160
  },
  {
    "content": "the sand letting the sand do the work for you it'll catch the paint from the",
    "start": 164
  },
  {
    "content": "brush unless you have some egregious misses don't worry about those tiny",
    "start": 168
  },
  {
    "content": "spots you might have missed that are showing through the black it's time to",
    "start": 176
  },
  {
    "content": "airbrush thanks to Vallejo for sending me these paints to try out I've used",
    "start": 180
  },
  {
    "content": "other acrylic miniature brand paints before but not Vallejo so I'm excited to",
    "start": 184
  },
  {
    "content": "try them out I'm gonna use sik green than S corp inna green and then moon",
    "start": 188
  },
  {
    "content": "yellow first up is sick green into the airbrush with some flow improver in",
    "start": 192
  },
  {
    "content": "water until it's the consistency of whole milk and away we go",
    "start": 197
  },
  {
    "content": "this piece doesn't have corners per se it has rounded corners and I'm just",
    "start": 200
  },
  {
    "content": "gonna trace all of those with a strong wide beam of this green few inches away",
    "start": 205
  },
  {
    "content": "30 psi on the compressor nearly full blast on the trigger I'm really",
    "start": 210
  },
  {
    "content": "impressed with the coverage here most anything over black doesn't show up well",
    "start": 214
  },
  {
    "content": "but this does if I go a little slower than my initial impulse it lays down",
    "start": 218
  },
  {
    "content": "strong enough without spidering that I only need one pass awesome so here it is",
    "start": 222
  },
  {
    "content": "all outlined and now on to the S Corp inna green very simple just gonna",
    "start": 228
  },
  {
    "content": "retrace everything I just did but not quite so wide maybe an inch closer and",
    "start": 232
  },
  {
    "content": "with the same amount of trigger action as before about three-quarters to full",
    "start": 237
  },
  {
    "content": "open nice starting to glow and arguably could call it here but I really want to",
    "start": 241
  },
  {
    "content": "intensify that green glow so loon yellow into the airbrush and retrace the final",
    "start": 246
  },
  {
    "content": "time now I'm only an inch away from the peace",
    "start": 251
  },
  {
    "content": "at this point dialed up the pressure to 36 psi and using 1/2 to 3/4 trigger",
    "start": 254
  },
  {
    "content": "action just kind of got to feel that out yes this has turned out exactly as I",
    "start": 259
  },
  {
    "content": "hoped it would on a final note you may see this doesn't sit flat if that's the",
    "start": 267
  },
  {
    "content": "case flip it over and paint on a layer of white PVA glue undiluted spread it",
    "start": 272
  },
  {
    "content": "out evenly with a brush or your finger making sure not to skimp on the edges",
    "start": 278
  },
  {
    "content": "honestly that's where it's most important give this 24 hours to dry even",
    "start": 282
  },
  {
    "content": "though it will seem dry after only 3 trust me leave it alone for the full 24",
    "start": 286
  },
  {
    "content": "hours fully cured and voila we've counteracted that warping a very good",
    "start": 290
  },
  {
    "content": "amount now I made a lot of these and I'm about to show you an entire tomb world",
    "start": 295
  },
  {
    "content": "city on a 6 by 4 foot table models and all but real quick if you liked this",
    "start": 298
  },
  {
    "content": "video please don't hesitate to hit the like button subscribe bell icon for",
    "start": 303
  },
  {
    "content": "reminders etc etc there is a link in the description below from my amazon",
    "start": 307
  },
  {
    "content": "storefront easy free way to support the channel if you want just buy your stuff",
    "start": 311
  },
  {
    "content": "through that link and for all you 3d printers out there while ochs crafting",
    "start": 315
  },
  {
    "content": "vids is sponsored by heroes horde which has an excellent range of high-quality",
    "start": 318
  },
  {
    "content": "models including but not limited to all true tiles lines which are open lock",
    "start": 322
  },
  {
    "content": "compatible also check out my modules over on the DMS guild and remember $3",
    "start": 327
  },
  {
    "content": "patrons get free copies of all my releases and here it is in all its glory",
    "start": 331
  },
  {
    "content": "I think I have 7 pieces on here in varying sizes I saved over the months",
    "start": 336
  },
  {
    "content": "and years finally had this use forum so I'm very happy with how it came out new",
    "start": 340
  },
  {
    "content": "world to battle on this is most of my necron models and they're about 95% done",
    "start": 344
  },
  {
    "content": "being painted so I apologize for the ones that aren't I was very happy with",
    "start": 349
  },
  {
    "content": "the Vallejo paints I'm kind of anal retentive if I wanted them to match my",
    "start": 354
  },
  {
    "content": "models and I was worried that the different shades of green wouldn't and",
    "start": 358
  },
  {
    "content": "they are different but it's really not noticeable on this scale the coverage is",
    "start": 361
  },
  {
    "content": "great they went through the airbrush fine so I'm excited to use them with a",
    "start": 364
  },
  {
    "content": "proper brush and try some other stuff now I don't know if there is a defined",
    "start": 368
  },
  {
    "content": "Canon view of what a necron tomb looks like aesthetically I'm sure if there is",
    "start": 373
  },
  {
    "content": "one of you will comment below and I would welcome the correction but for me",
    "start": 378
  },
  {
    "content": "free buildings that I just had to spend a couple hours painting up it was worth",
    "start": 382
  },
  {
    "content": "it so this is what my Necron tombs look like by the way if the idea of turning",
    "start": 386
  },
  {
    "content": "trash into terrain is interesting to you you gotta go find commissar games on",
    "start": 391
  },
  {
    "content": "YouTube watch his playlist on trash - terrain",
    "start": 395
  },
  {
    "content": "awesome tutorials very accessible for an amateur like myself also everything you",
    "start": 398
  },
  {
    "content": "see on the table we've built before on the channel it's from a previous episode",
    "start": 403
  },
  {
    "content": "so if you're interested in it go look through the backlog halfway through this",
    "start": 406
  },
  {
    "content": "I suddenly got the urge to rebase my HQ models so I did and I'll show you that",
    "start": 411
  },
  {
    "content": "in an upcoming episode oh and here's my objective markers I'm actually using the",
    "start": 415
  },
  {
    "content": "translucent green sprue left over bits that you get with Necron kits and I use",
    "start": 419
  },
  {
    "content": "those to make crystals that are poking out there the number of crystals tells",
    "start": 423
  },
  {
    "content": "you which objective marker it is working our way around the back street here up",
    "start": 427
  },
  {
    "content": "to the unit of lich guard ten of them which i have never in eight games ever",
    "start": 432
  },
  {
    "content": "gotten into close combat annoying and then over here a crystal cluster around",
    "start": 436
  },
  {
    "content": "this weird monolith thing again those are in previous episodes low and on the",
    "start": 444
  },
  {
    "content": "seventh day did it my poor airbrush rest but it took it like a champ still",
    "start": 450
  },
  {
    "content": "working fine I wanna HPC s love it if you liked this",
    "start": 455
  },
  {
    "content": "particular project here's two more that you should go check out right now also",
    "start": 459
  },
  {
    "content": "enjoy this month's community showcase and don't forget to subscribe and click",
    "start": 462
  },
  {
    "content": "that bell reminder icon I am why lock thanks for joining me and I'll see you",
    "start": 466
  },
  {
    "content": "next time",
    "start": 470
  }
]
