{
  "description": "BUY THE MINWAX SPRAY: http://amzn.to/2moLAfC\n(As an Amazon Associate I earn from qualifying purchases)\n\nHow to seal and protect your terrain made from styrofoam or foamcore board. This is the easiest way to make your pieces durable enough for the game table. \n\nJoin us on facebook: https://www.facebook.com/Black-Magic-Craft-677344725740094/?ref=bookmarks\n\nBlack Magic Craft title music by Black Magic Craft\n\nBackground music:\nKevin MacLeod (incompetech.com)\nhttp://creativecommons.org/licenses/by/3.0/",
  "id": "MNyf69SWJ88",
  "position": 9,
  "publishedAt": 1476151575,
  "thumbnails": {
    "default": "https://i.ytimg.com/vi/MNyf69SWJ88/sddefault.jpg",
    "large": "https://i.ytimg.com/vi/MNyf69SWJ88/maxresdefault.jpg",
    "small": "https://i.ytimg.com/vi/MNyf69SWJ88/mqdefault.jpg"
  },
  "title": "How to Seal and Protect Styrofoam Terrain (Episode 010)"
}
