[
  {
    "content": "hello my hot glue loving friends we're back for episode 9 of black magic crafts",
    "start": 30
  },
  {
    "content": "and some good news our friend Steve is back with us after a paint eating",
    "start": 37
  },
  {
    "content": "incident related suspension today we're going to continue on our nautical theme",
    "start": 47
  },
  {
    "content": "that we started last episode I'm sure all of you have built your long boats",
    "start": 53
  },
  {
    "content": "actually I know some of you built them immediately after the episode launched",
    "start": 60
  },
  {
    "content": "like the next day I get sent this play this Mike Harris like the day after the",
    "start": 67
  },
  {
    "content": "video came out made this awesome longbow template's man templates are they're",
    "start": 75
  },
  {
    "content": "great anyway now that you have this badass ship some of the cools got to",
    "start": 82
  },
  {
    "content": "happen your party is out on a nice relaxing cruise and all of a sudden the",
    "start": 90
  },
  {
    "content": "boat is under attack by a giant octopus squid Kraken beast Cthulhu thing",
    "start": 102
  },
  {
    "content": "whatever something with tentacles you need to make a set of these creepy",
    "start": 109
  },
  {
    "content": "looking tentacles so this project it all started on somebody posted on the DM",
    "start": 118
  },
  {
    "content": "Scotty Facebook group some photos of some octopus pens that they bought at",
    "start": 126
  },
  {
    "content": "Dollar Tree now full disclosure this project does break one of my rules for",
    "start": 132
  },
  {
    "content": "black magic craft tutorials that rule is that I don't use materials that you",
    "start": 138
  },
  {
    "content": "aren't going to easily be able to get now I know I use a",
    "start": 144
  },
  {
    "content": "lot of extruded polystyrene and some of you can't get that but it is something",
    "start": 147
  },
  {
    "content": "available across the world in hardware stores whereas these are a very specific",
    "start": 152
  },
  {
    "content": "toy from a specific store however they're just too perfect and also I",
    "start": 157
  },
  {
    "content": "think it likely that you'll be able to find them if you have a Dollar Tree in",
    "start": 166
  },
  {
    "content": "your city and I know most of you do because everyone on the Facebook group",
    "start": 169
  },
  {
    "content": "is always talking about Dollar Tree now when these were posted online I thought",
    "start": 173
  },
  {
    "content": "ah they won't have them at my Dollar Tree but you know what I checked and lo",
    "start": 179
  },
  {
    "content": "and behold they did right at the front amongst all the crap by the tails",
    "start": 184
  },
  {
    "content": "there's a bucket of different stupid pans and a whole bunch of them are these",
    "start": 188
  },
  {
    "content": "technical ones so you're going to need to go out to a Dollar Tree and see if",
    "start": 193
  },
  {
    "content": "you can find them however failing that this build can be done with basically",
    "start": 198
  },
  {
    "content": "any kind of hollow octopus toy you can take these principles and use them on",
    "start": 204
  },
  {
    "content": "with a different toy or even a different project basically what it comes down to",
    "start": 211
  },
  {
    "content": "is we took a cheap crappy rubber toy put an armature and it made them solid and",
    "start": 215
  },
  {
    "content": "painted them up without further ado let's build some tentacles alright first",
    "start": 220
  },
  {
    "content": "you're going to need to make some armature so that you can have your",
    "start": 236
  },
  {
    "content": "tentacles and various poses I use them 14 gauge electrical wire with the outer",
    "start": 238
  },
  {
    "content": "sheathing removed and to avoid having the wire poked through the soft rubber I",
    "start": 244
  },
  {
    "content": "coated the end of each one with a blob of hot glue next I take the wire and",
    "start": 248
  },
  {
    "content": "feed it into the tentacle making sure that the end reaches the very tip you'll",
    "start": 253
  },
  {
    "content": "need to fill these pieces with something to make them solid so that they can't",
    "start": 258
  },
  {
    "content": "squish causing the paint to crack on the soft rubber I use great stuff expanding",
    "start": 261
  },
  {
    "content": "foam it's important that you use the door and window variety as it has the",
    "start": 266
  },
  {
    "content": "lowest expansion rate feed the spray foam tube right to the",
    "start": 271
  },
  {
    "content": "tip of the tentacle and slowly and carefully fill with foam work your way",
    "start": 275
  },
  {
    "content": "down to the bottom trying to avoid both over filling and leaving gaps it's a bit",
    "start": 279
  },
  {
    "content": "tricky as the foam expands over time but you'll get the hang of it",
    "start": 284
  },
  {
    "content": "give the foam a few hours to expand and cure once the foam is cured cut off all",
    "start": 288
  },
  {
    "content": "the excess at this point you can also adjust the pose of each one by bending",
    "start": 299
  },
  {
    "content": "the wire armature to base these I use some two-inch washers with some wax",
    "start": 304
  },
  {
    "content": "paper underneath I fill in the hole of each washer with some hot glue making a",
    "start": 313
  },
  {
    "content": "pile of glue big enough to attach the tentacle then using more hot glue add a",
    "start": 317
  },
  {
    "content": "bit of texture around the edges to start building up the water to give the bases",
    "start": 323
  },
  {
    "content": "a bit more realistic wave look I use some white acrylic latex caulking and",
    "start": 331
  },
  {
    "content": "smear it over the surface and sculpt in some waves",
    "start": 336
  },
  {
    "content": "using a craft stick or a wet finger to kind of pull up little wave crests let",
    "start": 341
  },
  {
    "content": "the caulking cure for a few hours before spray bombing with black paint this is",
    "start": 347
  },
  {
    "content": "one case where you do want to make sure you use spray paint rather than just",
    "start": 351
  },
  {
    "content": "black acrylic craft paint it'll stick better to the rubber for the first coat",
    "start": 354
  },
  {
    "content": "of color I use a vibrant dark purple and this could take you a few coats then",
    "start": 359
  },
  {
    "content": "with a little bit of white add it to the purple I hit the tops of the suction",
    "start": 365
  },
  {
    "content": "cups I then mix in some turquoise with my",
    "start": 369
  },
  {
    "content": "purple to create a contrasting shade for the underside of the tentacles between",
    "start": 374
  },
  {
    "content": "the suction cups after repeating the first few coats of paint on the",
    "start": 379
  },
  {
    "content": "tentacles I put a coat of dark blue on the base water at this point they have a",
    "start": 384
  },
  {
    "content": "rather cartoonish look so you want to tone it down a bit by doing several",
    "start": 389
  },
  {
    "content": "coats with a black wash then using a lighter blue eye dry brush the crests of",
    "start": 394
  },
  {
    "content": "the waves on the basis for the last bit of paint work I use a white to dry brush",
    "start": 405
  },
  {
    "content": "the very tips of all the waves giving it that foamy water look I also pull some",
    "start": 415
  },
  {
    "content": "of this paint up onto the lower part of the tentacles so it looks like the water",
    "start": 421
  },
  {
    "content": "is actually splashing up around it in the final step is to give everything",
    "start": 425
  },
  {
    "content": "several coats with a spray gloss varnish I used a brand called minnow ax but any",
    "start": 438
  },
  {
    "content": "brand will do this will give everything a nice wet look and it will also help",
    "start": 443
  },
  {
    "content": "protect the paint on the soft rubber from cracking and chipping by giving",
    "start": 447
  },
  {
    "content": "everything a nice hard shell the finished pieces look great and I'm super",
    "start": 451
  },
  {
    "content": "happy with the results they do have some text embossed on them that you can see",
    "start": 459
  },
  {
    "content": "in this close-up but it's not really noticeable in the game table if you're",
    "start": 463
  },
  {
    "content": "really concerned about it you could shave that off before starting the build",
    "start": 466
  },
  {
    "content": "alright guys I hope you found this tutorial helpful if you did hit a like",
    "start": 470
  },
  {
    "content": "on the video if you aren't already a subscriber go below hit subscribe we are",
    "start": 478
  },
  {
    "content": "putting out awesome tutorials at the speed of moderately often but try to",
    "start": 485
  },
  {
    "content": "always put a quality work so you won't be disappointed also if you want to head",
    "start": 494
  },
  {
    "content": "on over to Facebook there's a black magic craft group there where I post",
    "start": 499
  },
  {
    "content": "random stuff link is in the description until next time",
    "start": 505
  }
]
