[
  {
    "content": "hello again why lock here make no mistake about it",
    "start": 12
  },
  {
    "content": "this video is going to be a little boring this is the preparations of the",
    "start": 16
  },
  {
    "content": "materials you'll need for the tiles I find it's best when doing mass",
    "start": 19
  },
  {
    "content": "production type work to cut everything out at once and make piles it's a lot",
    "start": 22
  },
  {
    "content": "easier to pull from as you assemble it so it's very simple without any ado",
    "start": 27
  },
  {
    "content": "let's get to it first up you'll need some sturdy",
    "start": 31
  },
  {
    "content": "cardstock this is medium weight chipboard that I'm working with",
    "start": 34
  },
  {
    "content": "chipboard is the stuff you'll find at the back of a legal pad of paper",
    "start": 39
  },
  {
    "content": "anything of thickness less than 1/16 of an inch will do but it must be sturdy",
    "start": 43
  },
  {
    "content": "cereal boxes and the like are not recommended the first thing to do is",
    "start": 48
  },
  {
    "content": "measure out one and a quarter inch squares and cut them out I'm",
    "start": 53
  },
  {
    "content": "fast-forwarding a lot here assuming you are able to use ruler and scissors now",
    "start": 56
  },
  {
    "content": "we have a large pile of one and a quarter inch squares set them aside do",
    "start": 65
  },
  {
    "content": "the exact same thing all over again except this time cut out one and 1/8",
    "start": 70
  },
  {
    "content": "inch squares instead slightly smaller again measuring and cutting squares is",
    "start": 74
  },
  {
    "content": "not worth your time so I will fast forward",
    "start": 79
  },
  {
    "content": "now we'll add features to the squares take your scissors and round off the",
    "start": 84
  },
  {
    "content": "corners irregularly no need to be perfect and in fact it should be",
    "start": 90
  },
  {
    "content": "different for each one once you've done that add some interesting feature to it",
    "start": 94
  },
  {
    "content": "I'll typically just put a small cut representing a crack but you could also",
    "start": 100
  },
  {
    "content": "do a chip do this for the small squares and the larger squares if you're an",
    "start": 105
  },
  {
    "content": "artistic person which I absolutely am NOT this would be the time to embellish",
    "start": 113
  },
  {
    "content": "the floor squares to your heart's content but be cautious the more details",
    "start": 117
  },
  {
    "content": "you add the more chaotic the floor will look when the final tiles are done too",
    "start": 122
  },
  {
    "content": "much going on can be a distraction and even make it hard to discern what's",
    "start": 126
  },
  {
    "content": "going on because if everything pops then nothing pops after a lot of",
    "start": 130
  },
  {
    "content": "experimentation I settled on the simple technique shown here of small cracks and",
    "start": 135
  },
  {
    "content": "chips allowing the paint job to create the detail later on next we will cut out",
    "start": 140
  },
  {
    "content": "the corrugation cladding this is thin black cardstock from Michaels 65 pound",
    "start": 146
  },
  {
    "content": "weight you do not want this material to be thick definitely do not use cereal",
    "start": 152
  },
  {
    "content": "box cardboard or chipboard here if you need to be very economical high quality",
    "start": 158
  },
  {
    "content": "printer paper will do that is the thickness you're aiming for the reason",
    "start": 164
  },
  {
    "content": "will become apparent later on we'll measure out quarter inch strips here and",
    "start": 168
  },
  {
    "content": "cut them next we get a hold of some dollar-store foam board specifically",
    "start": 173
  },
  {
    "content": "this is the one dollar per board stuff from Dollar Tree that DM Scotty",
    "start": 180
  },
  {
    "content": "recommended it is 3/16 of an inch thick and that is a very very important detail",
    "start": 185
  },
  {
    "content": "for later on do not attempt to buy the 5 dollar stuff at the craft store because",
    "start": 191
  },
  {
    "content": "believe it or not it will not work for this application because the glue",
    "start": 196
  },
  {
    "content": "holding the paper to the foam is too strong all we're doing here is cutting",
    "start": 200
  },
  {
    "content": "out half inch strips of the foam board next up we'll cut what I refer to as the",
    "start": 205
  },
  {
    "content": "foundations these are the two and a half by two and a half inch cardboard bases",
    "start": 217
  },
  {
    "content": "to which we'll attach the walls and the squares you'll need double corrugated",
    "start": 222
  },
  {
    "content": "cardboard but before we start cutting we need to discuss some very important",
    "start": 227
  },
  {
    "content": "nuances now our tiles need an overall width of two and a half inches however",
    "start": 232
  },
  {
    "content": "those black corrugation cover strips from earlier will have some thickness",
    "start": 239
  },
  {
    "content": "even if it is very small additionally ever-so-slightly small is better than",
    "start": 243
  },
  {
    "content": "ever so slightly large because the error can be compensated for on the game table",
    "start": 248
  },
  {
    "content": "and therefore will not propagate so you should cut your foundations not at two",
    "start": 253
  },
  {
    "content": "and a half inches but rather at two and 1530 seconds of an inch or as it is",
    "start": 258
  },
  {
    "content": "referred to in carpentry two and a half light most rulers show sixteenths of an",
    "start": 264
  },
  {
    "content": "inch you are aiming between two of those marks this is the size for a field tile",
    "start": 269
  },
  {
    "content": "or a tile that has no walls there is another consideration for non filled",
    "start": 276
  },
  {
    "content": "tiles because of their walls for my modular tiles the walls are built as",
    "start": 281
  },
  {
    "content": "follows here's the foundation and here's the squares at the top a strip of",
    "start": 286
  },
  {
    "content": "chipboard will be hot glued to the side of the foundation then foam board will",
    "start": 293
  },
  {
    "content": "be glued to both the chipboard and the foundation I did it this way in order to",
    "start": 298
  },
  {
    "content": "provide two axes of control and you will be surprised at how strong these walls",
    "start": 303
  },
  {
    "content": "are anyway there is clearly a problem the thickness of the chipboard has",
    "start": 307
  },
  {
    "content": "pushed our tiles width beyond two and a half inches",
    "start": 313
  },
  {
    "content": "therefore the foundation itself needs to be smaller from the very beginning",
    "start": 316
  },
  {
    "content": "specifically for the tile above you'd cut the foundation at two and seven",
    "start": 321
  },
  {
    "content": "sixteenths of an inch remember when I mentioned earlier that your chipboard",
    "start": 326
  },
  {
    "content": "should be a sixteenth of an inch or less this is why for the various tile",
    "start": 330
  },
  {
    "content": "configurations here are the foundation sizes that you should use",
    "start": 336
  },
  {
    "content": "I recommend you label your foundations since they will differ in size ever so",
    "start": 346
  },
  {
    "content": "slightly finally we need to cut out the walls from chipboard or whatever sturdy",
    "start": 352
  },
  {
    "content": "stock you've been using simply cut strips that are three quarters of an",
    "start": 358
  },
  {
    "content": "inch wide then cut them to width not two and a half inches but two and a half",
    "start": 362
  },
  {
    "content": "light remember that means halfway between the sixteenth marks on the ruler",
    "start": 368
  },
  {
    "content": "now we have everything we need to begin assembly fire up your hot glue gun and",
    "start": 373
  },
  {
    "content": "join me in video 3 you",
    "start": 378
  }
]
